[
  {
    "id": 1,
    "name": "Image 1",
    "image": "./assets/images/image1.jpg"
  },
  {
    "id": 2,
    "name": "Image 2",
    "image": "./assets/images/image2.jpg"
  },
  {
    "id": 3,
    "name": "Image 3",
    "image": "./assets/images/image3.jpg"
  },
  {
    "id": 4,
    "name": "Image 4",
    "image": "./assets/images/image4.jpg"
  },
  {
    "id": 5,
    "name": "Image 5",
    "image": "./assets/images/image5.jpg"
  },
  {
    "id": 6,
    "name": "Image 6",
    "image": "./assets/images/image6.jpg"
  },
  {
    "id": 7,
    "name": "Image 7",
    "image": "./assets/images/image7.jpg"
  },
  {
    "id": 8,
    "name": "Image 8",
    "image": "./assets/images/image8.jpg"
  },  {
    "id": 9,
    "name": "Image 9",
    "image": "./assets/images/image9.jpg"
  },
  {
    "id": 10,
    "name": "Image 10",
    "image": "./assets/images/image10.jpg"
  },
  {
    "id": 11,
    "name": "Image 11",
    "image": "./assets/images/image11.jpg"
  },
  {
    "id": 12,
    "name": "Image 12",
    "image": "./assets/images/image12.jpg"
  }


]
